databench/__init__.py
databench/analysis.py
databench/analysis_zmq.py
databench/app.py
databench/cli.py
databench/datastore.py
databench/datastore_legacy.py
databench/meta.py
databench/meta_zmq.py
databench/readme.py
databench/scaffold.py
databench/template.py
databench/testing.py
databench/utils.py
databench/analyses_packaged/README.md
databench/analyses_packaged/__init__.py
databench/analyses_packaged/index.yaml
databench/analyses_packaged/dummypi/README.md
databench/analyses_packaged/dummypi/__init__.py
databench/analyses_packaged/dummypi/analysis.js
databench/analyses_packaged/dummypi/analysis.py
databench/analyses_packaged/dummypi/index.html
databench/analyses_packaged/dummypi/thumbnail.png
databench/analyses_packaged/dummypi_py/README.md
databench/analyses_packaged/dummypi_py/analysis.js
databench/analyses_packaged/dummypi_py/analysis.py
databench/analyses_packaged/dummypi_py/index.html
databench/analyses_packaged/dummypi_py/thumbnail.png
databench/analyses_packaged/scaffold/README.md
databench/analyses_packaged/scaffold/__init__.py
databench/analyses_packaged/scaffold/analysis.js
databench/analyses_packaged/scaffold/analysis.py
databench/analyses_packaged/scaffold/index.html
databench/analyses_packaged/scaffold/thumbnail.png
databench/analyses_packaged/scaffold_py/README.md
databench/analyses_packaged/scaffold_py/analysis.js
databench/analyses_packaged/scaffold_py/analysis.py
databench/analyses_packaged/scaffold_py/index.html
databench/analyses_packaged/scaffold_py/thumbnail.png
databench/static/databench.css
databench/static/databench.js
databench/static/databench.js.map
databench/static/favicon.ico
databench/static/logo.svg
databench/templates/analysis.html
databench/templates/base.html
databench/templates/index.html
databench/tests/__init__.py
databench/tests/test_action_decorator.py
databench/tests/test_analysistest.py
databench/tests/test_build.py
databench/tests/test_datastore.py
databench/tests/test_json_encoder.py
databench/tests/test_node_client.py
databench-0.7.3.dist-info/LICENSE
databench-0.7.3.dist-info/METADATA
databench-0.7.3.dist-info/WHEEL
databench-0.7.3.dist-info/entry_points.txt
databench-0.7.3.dist-info/top_level.txt
databench-0.7.3.dist-info/RECORD
