Metadata-Version: 2.1
Name: databench
Version: 0.7.3
Summary: Realtime data analysis tool.
Home-page: https://github.com/svenkreiss/databench
Author: Sven Kreiss
Author-email: me@svenkreiss.com
License: MIT
Platform: UNKNOWN
Classifier: Development Status :: 4 - Beta
Classifier: Intended Audience :: Developers
Classifier: Intended Audience :: Science/Research
Classifier: Natural Language :: English
Classifier: License :: OSI Approved :: MIT License
Classifier: Operating System :: OS Independent
Classifier: Programming Language :: Python
Classifier: Programming Language :: Python :: 2
Classifier: Programming Language :: Python :: 2.7
Classifier: Programming Language :: Python :: 3
Classifier: Programming Language :: Python :: 3.4
Classifier: Programming Language :: Python :: 3.5
Classifier: Programming Language :: Python :: 3.6
Requires-Dist: docutils (>=0.12)
Requires-Dist: future (>=0.15)
Requires-Dist: markdown (>=2.6.5)
Requires-Dist: pyyaml (>=3.11)
Requires-Dist: pyzmq (>=4.3.1)
Requires-Dist: tornado (>=4.3)
Requires-Dist: wrapt (>=1.10.11)
Provides-Extra: tests
Requires-Dist: coverage (>=4.4.2) ; extra == 'tests'
Requires-Dist: ghp-import (>=0.4.1) ; extra == 'tests'
Requires-Dist: hacking (>=0.11.0) ; extra == 'tests'
Requires-Dist: html5validator (>=0.2.6) ; extra == 'tests'
Requires-Dist: localcrawl (>=0.2.3) ; extra == 'tests'
Requires-Dist: matplotlib (>=1.5.1) ; extra == 'tests'
Requires-Dist: nose (>=1.3.4) ; extra == 'tests'
Requires-Dist: requests (>=2.9.1) ; extra == 'tests'
Requires-Dist: websocket-client (>=0.35.0) ; extra == 'tests'
